Pytorch_Easy
